ai_startup_diagnosis/__init__.py
ai_startup_diagnosis/config.py
ai_startup_diagnosis/main.py
ai_startup_diagnosis/api/__init__.py
ai_startup_diagnosis/api/auth.py
ai_startup_diagnosis/api/diagnostic.py
ai_startup_diagnosis/models/__init__.py
ai_startup_diagnosis/models/schemas.py
ai_startup_diagnosis/services/__init__.py
ai_startup_diagnosis/services/ai_service.py
ai_startup_diagnosis/services/rate_limiter.py
ai_startup_diagnosis/utils/__init__.py
ai_startup_diagnosis/utils/error_handler.py
ai_startup_diagnosis-0.2.1.dist-info/licenses/LICENSE
ai_startup_diagnosis-0.2.1.dist-info/METADATA
ai_startup_diagnosis-0.2.1.dist-info/WHEEL
ai_startup_diagnosis-0.2.1.dist-info/entry_points.txt
ai_startup_diagnosis-0.2.1.dist-info/top_level.txt
ai_startup_diagnosis-0.2.1.dist-info/RECORD
