Metadata-Version: 2.4
Name: ai-startup-diagnosis
Version: 0.2.1
Summary: AI-powered startup readiness diagnosis API with FastAPI
Author-email: Willinghood <info@willinghood.com>
License-Expression: MIT
Project-URL: Homepage, https://github.com/willinghood/ai-startup-diagnosis
Project-URL: Documentation, https://github.com/willinghood/ai-startup-diagnosis#readme
Project-URL: Repository, https://github.com/willinghood/ai-startup-diagnosis
Project-URL: Issues, https://github.com/willinghood/ai-startup-diagnosis/issues
Keywords: startup,diagnosis,ai,openai,fastapi,api
Classifier: Development Status :: 4 - Beta
Classifier: Intended Audience :: Developers
Classifier: Programming Language :: Python :: 3
Classifier: Topic :: Software Development :: Libraries :: Python Modules
Classifier: Topic :: Internet :: WWW/HTTP :: HTTP Servers
Requires-Python: >=3.9
License-File: LICENSE
Requires-Dist: fastapi>=0.104.1
Requires-Dist: uvicorn[standard]>=0.24.0
Requires-Dist: pydantic>=2.5.0
Requires-Dist: pydantic-settings>=2.1.0
Requires-Dist: httpx>=0.25.2
Requires-Dist: slowapi>=0.1.9
Provides-Extra: dev
Requires-Dist: pytest>=7.0.0; extra == "dev"
Requires-Dist: pytest-asyncio>=0.21.0; extra == "dev"
Requires-Dist: black>=23.0.0; extra == "dev"
Requires-Dist: ruff>=0.1.0; extra == "dev"
Dynamic: license-file
